ioumatch/__init__.py
ioumatch/iou.py
ioumatch/matching.py
ioumatch/metrics.py
ioumatch/utils.py
ioumatch-0.1.0.dist-info/licenses/LICENSE
ioumatch-0.1.0.dist-info/METADATA
ioumatch-0.1.0.dist-info/WHEEL
ioumatch-0.1.0.dist-info/top_level.txt
ioumatch-0.1.0.dist-info/RECORD
