Metadata-Version: 2.4
Name: ioumatch
Version: 0.1.0
Summary: Compute IoU matrices and one-to-one matching for segmentation evaluation
Home-page: https://github.com/al-alec/ioumatch
Author: Alexis Yehadji
Author-email: yehadjialexis@gmail.com
License: MIT
Requires-Python: >=3.6
License-File: LICENSE
Dynamic: author-email
Dynamic: home-page
Dynamic: license-file
Dynamic: requires-python
